Metadata-Version: 2.1
Name: django-postalcodes-mexico
Version: 0.6.1
Summary: A Django Package for handling Mexico's postal codes
Home-page: https://github.com/EduardoZepeda/django-postalcodes-mexico
Author: Eduardo Zepeda
Author-email: eduardozepeda@coffeebytes.dev
License: MIT
Keywords: django-postalcodes-mexico
Classifier: Development Status :: 4 - Beta
Classifier: Framework :: Django :: 3.1
Classifier: Framework :: Django :: 3.2
Classifier: Framework :: Django :: 4.1
Classifier: Framework :: Django :: 5.0
Classifier: Intended Audience :: Developers
Classifier: License :: OSI Approved :: BSD License
Classifier: Natural Language :: English
Classifier: Programming Language :: Python :: 3.10
Classifier: Programming Language :: Python :: 3.11
Classifier: Programming Language :: Python :: 3.12
License-File: LICENSE
License-File: AUTHORS.rst
Requires-Dist: django-model-utils>=4.3.1
Requires-Dist: requests>=2.25.1
